int_input/__init__.py
int_input/int_input.py
the_package/__init__.py
the_package/int_input.py
int_input_hohfchns-0.0.3.dist-info/LICENSE
int_input_hohfchns-0.0.3.dist-info/METADATA
int_input_hohfchns-0.0.3.dist-info/WHEEL
int_input_hohfchns-0.0.3.dist-info/top_level.txt
int_input_hohfchns-0.0.3.dist-info/RECORD
