Metadata-Version: 2.1
Name: int-input-hohfchns
Version: 0.0.3
Summary: A simple function to get only integer input
Home-page: https://github.com/hohfchns/My-Python-Modules/blob/master/int_input.py
Author: hohfchns
Author-email: hohfchns@example.com
License: UNKNOWN
Platform: UNKNOWN
Classifier: Programming Language :: Python :: 3
Classifier: License :: OSI Approved :: MIT License
Classifier: Operating System :: OS Independent
Requires-Python: >=3.7
